HISTORY.md
LICENSE
MANIFEST.in
README.md
requirements.txt
setup.py
tweeta/__init__.py
tweeta/constants.py
tweeta/exceptions.py
tweeta/text.py
tweeta/tweet.py
tweeta.egg-info/PKG-INFO
tweeta.egg-info/SOURCES.txt
tweeta.egg-info/dependency_links.txt
tweeta.egg-info/requires.txt
tweeta.egg-info/top_level.txt