Metadata-Version: 1.1
Name: tweeta
Version: 0.2.1
Summary: A collection utitlity funtions to process Twittwer data (e.g., turn raw json into python object with safe checks)
Home-page: https://github.com/bianjiang/tweeta
Author: Jiang Bian
Author-email: ji0ng.bi0n@gmail.com
License: The MIT License
